{
    "last_update": "2026-06-22 04:17:34",
    "next_update": "2026-06-22 04:22:34",
    "domains": [
        {
            "domain": "minitotobesar.site",
            "nawala": false,
            "network": false,
            "checked_at": "2026-06-22 04:15:19"
        },
        {
            "domain": "minipasticuan.com",
            "nawala": false,
            "network": false,
            "checked_at": "2026-06-22 04:15:21"
        },
        {
            "domain": "minimasihdisini.com",
            "nawala": false,
            "network": false,
            "checked_at": "2026-06-22 04:15:22"
        },
        {
            "domain": "ampmini.it.com",
            "nawala": false,
            "network": false,
            "checked_at": "2026-06-22 04:15:23"
        },
        {
            "domain": "oldhamcounty.b-cdn.net",
            "nawala": false,
            "network": false,
            "checked_at": "2026-06-22 04:15:24"
        },
        {
            "domain": "minibisa.com",
            "nawala": false,
            "network": false,
            "checked_at": "2026-06-22 04:15:33"
        },
        {
            "domain": "gandacuan.com",
            "nawala": false,
            "network": false,
            "checked_at": "2026-06-22 04:15:41"
        },
        {
            "domain": "gandacuan.id",
            "nawala": false,
            "network": false,
            "checked_at": "2026-06-22 04:15:43"
        },
        {
            "domain": "gandacuan.io",
            "nawala": false,
            "network": false,
            "checked_at": "2026-06-22 04:15:58"
        },
        {
            "domain": "mariminisantai.web.app/",
            "nawala": false,
            "network": false,
            "checked_at": "2026-06-22 04:16:15"
        },
        {
            "domain": "gandacuan.cc",
            "nawala": false,
            "network": false,
            "checked_at": "2026-06-22 04:16:30"
        },
        {
            "domain": "minikenangan.com",
            "nawala": false,
            "network": false,
            "checked_at": "2026-06-22 04:16:50"
        },
        {
            "domain": "rtp.panelgandacuan.com",
            "nawala": false,
            "network": false,
            "checked_at": "2026-06-22 04:16:51"
        },
        {
            "domain": "prediksi.panelgandacuan.com",
            "nawala": false,
            "network": false,
            "checked_at": "2026-06-22 04:17:31"
        },
        {
            "domain": "promosi.panelgandacuan.com",
            "nawala": false,
            "network": false,
            "checked_at": "2026-06-22 04:17:32"
        },
        {
            "domain": "panduan.panelgandacuan.com",
            "nawala": false,
            "network": false,
            "checked_at": "2026-06-22 04:17:33"
        },
        {
            "domain": "minisayang.com",
            "nawala": false,
            "network": false,
            "checked_at": "2026-06-22 04:17:34"
        }
    ]
}