{
    "last_update": "2026-06-20 03:11:27",
    "next_update": "2026-06-20 03:16:27",
    "domains": [
        {
            "domain": "minitotobesar.site",
            "nawala": false,
            "network": false,
            "checked_at": "2026-06-20 03:11:12"
        },
        {
            "domain": "minipasticuan.com",
            "nawala": false,
            "network": false,
            "checked_at": "2026-06-20 03:11:13"
        },
        {
            "domain": "minimasihdisini.com",
            "nawala": false,
            "network": false,
            "checked_at": "2026-06-20 03:11:14"
        },
        {
            "domain": "ampmini.it.com",
            "nawala": false,
            "network": false,
            "checked_at": "2026-06-20 03:11:14"
        },
        {
            "domain": "oldhamcounty.b-cdn.net",
            "nawala": false,
            "network": false,
            "checked_at": "2026-06-20 03:11:15"
        },
        {
            "domain": "minibisa.com",
            "nawala": false,
            "network": false,
            "checked_at": "2026-06-20 03:11:17"
        },
        {
            "domain": "gandacuan.com",
            "nawala": false,
            "network": false,
            "checked_at": "2026-06-20 03:11:18"
        },
        {
            "domain": "gandacuan.id",
            "nawala": false,
            "network": false,
            "checked_at": "2026-06-20 03:11:19"
        },
        {
            "domain": "gandacuan.io",
            "nawala": false,
            "network": false,
            "checked_at": "2026-06-20 03:11:19"
        },
        {
            "domain": "mariminisantai.web.app/",
            "nawala": false,
            "network": false,
            "checked_at": "2026-06-20 03:11:20"
        },
        {
            "domain": "gandacuan.cc",
            "nawala": false,
            "network": false,
            "checked_at": "2026-06-20 03:11:21"
        },
        {
            "domain": "minikenangan.com",
            "nawala": false,
            "network": false,
            "checked_at": "2026-06-20 03:11:22"
        },
        {
            "domain": "rtp.panelgandacuan.com",
            "nawala": false,
            "network": false,
            "checked_at": "2026-06-20 03:11:23"
        },
        {
            "domain": "buktijp.panelgandacuan.com",
            "nawala": false,
            "network": false,
            "checked_at": "2026-06-20 03:11:24"
        },
        {
            "domain": "prediksi.panelgandacuan.com",
            "nawala": false,
            "network": false,
            "checked_at": "2026-06-20 03:11:25"
        },
        {
            "domain": "promosi.panelgandacuan.com",
            "nawala": false,
            "network": false,
            "checked_at": "2026-06-20 03:11:25"
        },
        {
            "domain": "panduan.panelgandacuan.com",
            "nawala": false,
            "network": false,
            "checked_at": "2026-06-20 03:11:26"
        },
        {
            "domain": "minisayang.com",
            "nawala": false,
            "network": false,
            "checked_at": "2026-06-20 03:11:27"
        }
    ]
}