{
    "last_update": "2026-06-19 17:33:17",
    "next_update": "2026-06-19 17:38:17",
    "domains": [
        {
            "domain": "minitotobesar.site",
            "nawala": false,
            "network": false,
            "checked_at": "2026-06-19 17:32:55"
        },
        {
            "domain": "minipasticuan.com",
            "nawala": false,
            "network": false,
            "checked_at": "2026-06-19 17:33:02"
        },
        {
            "domain": "minimasihdisini.com",
            "nawala": false,
            "network": false,
            "checked_at": "2026-06-19 17:33:04"
        },
        {
            "domain": "ampmini.it.com",
            "nawala": false,
            "network": false,
            "checked_at": "2026-06-19 17:33:05"
        },
        {
            "domain": "oldhamcounty.b-cdn.net",
            "nawala": false,
            "network": false,
            "checked_at": "2026-06-19 17:33:06"
        },
        {
            "domain": "minibisa.com",
            "nawala": false,
            "network": false,
            "checked_at": "2026-06-19 17:33:07"
        },
        {
            "domain": "gandacuan.com",
            "nawala": false,
            "network": false,
            "checked_at": "2026-06-19 17:33:08"
        },
        {
            "domain": "gandacuan.id",
            "nawala": false,
            "network": false,
            "checked_at": "2026-06-19 17:33:08"
        },
        {
            "domain": "gandacuan.io",
            "nawala": false,
            "network": false,
            "checked_at": "2026-06-19 17:33:09"
        },
        {
            "domain": "mariminisantai.web.app/",
            "nawala": false,
            "network": false,
            "checked_at": "2026-06-19 17:33:10"
        },
        {
            "domain": "gandacuan.cc",
            "nawala": false,
            "network": false,
            "checked_at": "2026-06-19 17:33:11"
        },
        {
            "domain": "minikenangan.com",
            "nawala": false,
            "network": false,
            "checked_at": "2026-06-19 17:33:12"
        },
        {
            "domain": "rtp.panelgandacuan.com",
            "nawala": false,
            "network": false,
            "checked_at": "2026-06-19 17:33:13"
        },
        {
            "domain": "buktijp.panelgandacuan.com",
            "nawala": false,
            "network": false,
            "checked_at": "2026-06-19 17:33:14"
        },
        {
            "domain": "prediksi.panelgandacuan.com",
            "nawala": false,
            "network": false,
            "checked_at": "2026-06-19 17:33:15"
        },
        {
            "domain": "promosi.panelgandacuan.com",
            "nawala": false,
            "network": false,
            "checked_at": "2026-06-19 17:33:16"
        },
        {
            "domain": "panduan.panelgandacuan.com",
            "nawala": false,
            "network": false,
            "checked_at": "2026-06-19 17:33:17"
        }
    ]
}