{
    "last_update": "2026-06-23 16:03:52",
    "next_update": "2026-06-23 16:08:52",
    "domains": [
        {
            "domain": "minitotobesar.site",
            "nawala": false,
            "network": false,
            "checked_at": "2026-06-23 16:03:36"
        },
        {
            "domain": "minipasticuan.com",
            "nawala": false,
            "network": false,
            "checked_at": "2026-06-23 16:03:37"
        },
        {
            "domain": "minimasihdisini.com",
            "nawala": false,
            "network": false,
            "checked_at": "2026-06-23 16:03:38"
        },
        {
            "domain": "ampmini.it.com",
            "nawala": false,
            "network": false,
            "checked_at": "2026-06-23 16:03:38"
        },
        {
            "domain": "oldhamcounty.b-cdn.net",
            "nawala": false,
            "network": false,
            "checked_at": "2026-06-23 16:03:39"
        },
        {
            "domain": "minibisa.com",
            "nawala": false,
            "network": false,
            "checked_at": "2026-06-23 16:03:40"
        },
        {
            "domain": "gandacuan.com",
            "nawala": false,
            "network": false,
            "checked_at": "2026-06-23 16:03:41"
        },
        {
            "domain": "gandacuan.id",
            "nawala": false,
            "network": false,
            "checked_at": "2026-06-23 16:03:42"
        },
        {
            "domain": "gandacuan.io",
            "nawala": false,
            "network": false,
            "checked_at": "2026-06-23 16:03:42"
        },
        {
            "domain": "mariminisantai.web.app/",
            "nawala": false,
            "network": false,
            "checked_at": "2026-06-23 16:03:44"
        },
        {
            "domain": "gandacuan.cc",
            "nawala": false,
            "network": false,
            "checked_at": "2026-06-23 16:03:45"
        },
        {
            "domain": "minikenangan.com",
            "nawala": false,
            "network": false,
            "checked_at": "2026-06-23 16:03:46"
        },
        {
            "domain": "rtp.panelgandacuan.com",
            "nawala": false,
            "network": false,
            "checked_at": "2026-06-23 16:03:46"
        },
        {
            "domain": "buktijp.panelgandacuan.com",
            "nawala": false,
            "network": false,
            "checked_at": "2026-06-23 16:03:48"
        },
        {
            "domain": "prediksi.panelgandacuan.com",
            "nawala": false,
            "network": false,
            "checked_at": "2026-06-23 16:03:49"
        },
        {
            "domain": "promosi.panelgandacuan.com",
            "nawala": false,
            "network": false,
            "checked_at": "2026-06-23 16:03:50"
        },
        {
            "domain": "panduan.panelgandacuan.com",
            "nawala": false,
            "network": false,
            "checked_at": "2026-06-23 16:03:51"
        },
        {
            "domain": "minisayang.com",
            "nawala": false,
            "network": false,
            "checked_at": "2026-06-23 16:03:52"
        }
    ]
}