{
    "last_update": "2026-06-13 21:26:34",
    "next_update": "2026-06-13 21:31:34",
    "domains": [
        {
            "domain": "miniyakin.com",
            "nawala": false,
            "network": false,
            "checked_at": "2026-06-13 21:26:20"
        },
        {
            "domain": "minitotobesar.site",
            "nawala": false,
            "network": false,
            "checked_at": "2026-06-13 21:26:21"
        },
        {
            "domain": "minimasihdisini.com",
            "nawala": false,
            "network": false,
            "checked_at": "2026-06-13 21:26:26"
        },
        {
            "domain": "ampmini.it.com",
            "nawala": false,
            "network": false,
            "checked_at": "2026-06-13 21:26:27"
        },
        {
            "domain": "oldhamcounty.b-cdn.net",
            "nawala": false,
            "network": false,
            "checked_at": "2026-06-13 21:26:28"
        },
        {
            "domain": "minibisa.com",
            "nawala": false,
            "network": false,
            "checked_at": "2026-06-13 21:26:29"
        },
        {
            "domain": "minimantul.com",
            "nawala": false,
            "network": false,
            "checked_at": "2026-06-13 21:26:30"
        },
        {
            "domain": "gandacuan.com",
            "nawala": false,
            "network": false,
            "checked_at": "2026-06-13 21:26:31"
        },
        {
            "domain": "gandacuan.id",
            "nawala": false,
            "network": false,
            "checked_at": "2026-06-13 21:26:32"
        },
        {
            "domain": "gandacuan.io",
            "nawala": false,
            "network": false,
            "checked_at": "2026-06-13 21:26:33"
        },
        {
            "domain": "mariminisantai.web.app/",
            "nawala": false,
            "network": false,
            "checked_at": "2026-06-13 21:26:34"
        }
    ]
}