{
    "last_update": "2026-06-21 23:53:02",
    "next_update": "2026-06-21 23:58:02",
    "domains": [
        {
            "domain": "minitotobesar.site",
            "nawala": false,
            "network": false,
            "checked_at": "2026-06-21 23:52:47"
        },
        {
            "domain": "minipasticuan.com",
            "nawala": false,
            "network": false,
            "checked_at": "2026-06-21 23:52:48"
        },
        {
            "domain": "minimasihdisini.com",
            "nawala": false,
            "network": false,
            "checked_at": "2026-06-21 23:52:49"
        },
        {
            "domain": "ampmini.it.com",
            "nawala": false,
            "network": false,
            "checked_at": "2026-06-21 23:52:50"
        },
        {
            "domain": "oldhamcounty.b-cdn.net",
            "nawala": false,
            "network": false,
            "checked_at": "2026-06-21 23:52:50"
        },
        {
            "domain": "minibisa.com",
            "nawala": false,
            "network": false,
            "checked_at": "2026-06-21 23:52:52"
        },
        {
            "domain": "gandacuan.com",
            "nawala": false,
            "network": false,
            "checked_at": "2026-06-21 23:52:53"
        },
        {
            "domain": "gandacuan.id",
            "nawala": false,
            "network": false,
            "checked_at": "2026-06-21 23:52:53"
        },
        {
            "domain": "gandacuan.io",
            "nawala": false,
            "network": false,
            "checked_at": "2026-06-21 23:52:54"
        },
        {
            "domain": "mariminisantai.web.app/",
            "nawala": false,
            "network": false,
            "checked_at": "2026-06-21 23:52:55"
        },
        {
            "domain": "gandacuan.cc",
            "nawala": false,
            "network": false,
            "checked_at": "2026-06-21 23:52:56"
        },
        {
            "domain": "minikenangan.com",
            "nawala": false,
            "network": false,
            "checked_at": "2026-06-21 23:52:57"
        },
        {
            "domain": "rtp.panelgandacuan.com",
            "nawala": false,
            "network": false,
            "checked_at": "2026-06-21 23:52:58"
        },
        {
            "domain": "prediksi.panelgandacuan.com",
            "nawala": false,
            "network": false,
            "checked_at": "2026-06-21 23:52:59"
        },
        {
            "domain": "promosi.panelgandacuan.com",
            "nawala": false,
            "network": false,
            "checked_at": "2026-06-21 23:53:01"
        },
        {
            "domain": "panduan.panelgandacuan.com",
            "nawala": false,
            "network": false,
            "checked_at": "2026-06-21 23:53:02"
        },
        {
            "domain": "minisayang.com",
            "nawala": false,
            "network": false,
            "checked_at": "2026-06-21 23:53:02"
        }
    ]
}