{
    "last_update": "2026-06-09 07:32:23",
    "next_update": "2026-06-09 07:37:23",
    "domains": [
        {
            "domain": "miniyakin.com",
            "nawala": false,
            "network": false,
            "checked_at": "2026-06-09 07:32:15"
        },
        {
            "domain": "minitotobesar.site",
            "nawala": false,
            "network": false,
            "checked_at": "2026-06-09 07:32:17"
        },
        {
            "domain": "minitoto.us",
            "nawala": false,
            "network": false,
            "checked_at": "2026-06-09 07:32:18"
        },
        {
            "domain": "minipasticuan.com",
            "nawala": false,
            "network": false,
            "checked_at": "2026-06-09 07:32:19"
        },
        {
            "domain": "minimasihdisini.com",
            "nawala": false,
            "network": false,
            "checked_at": "2026-06-09 07:32:20"
        },
        {
            "domain": "minitotopauss.firebaseapp.com",
            "nawala": false,
            "network": false,
            "checked_at": "2026-06-09 07:32:20"
        },
        {
            "domain": "ampmini.it.com",
            "nawala": false,
            "network": false,
            "checked_at": "2026-06-09 07:32:21"
        },
        {
            "domain": "oldhamcounty.b-cdn.net",
            "nawala": false,
            "network": false,
            "checked_at": "2026-06-09 07:32:23"
        }
    ]
}