{
    "last_update": "2026-06-17 21:11:23",
    "next_update": "2026-06-17 21:16:23",
    "domains": [
        {
            "domain": "minitotobesar.site",
            "nawala": false,
            "network": false,
            "checked_at": "2026-06-17 21:11:11"
        },
        {
            "domain": "minipasticuan.com",
            "nawala": false,
            "network": false,
            "checked_at": "2026-06-17 21:11:12"
        },
        {
            "domain": "minimasihdisini.com",
            "nawala": false,
            "network": false,
            "checked_at": "2026-06-17 21:11:13"
        },
        {
            "domain": "ampmini.it.com",
            "nawala": false,
            "network": false,
            "checked_at": "2026-06-17 21:11:14"
        },
        {
            "domain": "oldhamcounty.b-cdn.net",
            "nawala": false,
            "network": false,
            "checked_at": "2026-06-17 21:11:15"
        },
        {
            "domain": "minibisa.com",
            "nawala": false,
            "network": false,
            "checked_at": "2026-06-17 21:11:16"
        },
        {
            "domain": "minimantul.com",
            "nawala": false,
            "network": false,
            "checked_at": "2026-06-17 21:11:17"
        },
        {
            "domain": "gandacuan.id",
            "nawala": false,
            "network": false,
            "checked_at": "2026-06-17 21:11:19"
        },
        {
            "domain": "gandacuan.io",
            "nawala": false,
            "network": false,
            "checked_at": "2026-06-17 21:11:20"
        },
        {
            "domain": "mariminisantai.web.app/",
            "nawala": false,
            "network": false,
            "checked_at": "2026-06-17 21:11:20"
        },
        {
            "domain": "gandacuan.cc",
            "nawala": false,
            "network": false,
            "checked_at": "2026-06-17 21:11:21"
        },
        {
            "domain": "minikenangan.com",
            "nawala": false,
            "network": false,
            "checked_at": "2026-06-17 21:11:23"
        }
    ]
}