{
    "last_update": "2026-06-10 16:34:14",
    "next_update": "2026-06-10 16:39:14",
    "domains": [
        {
            "domain": "miniyakin.com",
            "nawala": false,
            "network": false,
            "checked_at": "2026-06-10 16:33:35"
        },
        {
            "domain": "minitotobesar.site",
            "nawala": false,
            "network": false,
            "checked_at": "2026-06-10 16:33:37"
        },
        {
            "domain": "minipasticuan.com",
            "nawala": false,
            "network": false,
            "checked_at": "2026-06-10 16:33:38"
        },
        {
            "domain": "minimasihdisini.com",
            "nawala": false,
            "network": false,
            "checked_at": "2026-06-10 16:33:39"
        },
        {
            "domain": "minitotopauss.firebaseapp.com",
            "nawala": false,
            "network": false,
            "checked_at": "2026-06-10 16:33:40"
        },
        {
            "domain": "ampmini.it.com",
            "nawala": false,
            "network": false,
            "checked_at": "2026-06-10 16:33:42"
        },
        {
            "domain": "oldhamcounty.b-cdn.net",
            "nawala": false,
            "network": false,
            "checked_at": "2026-06-10 16:33:43"
        }
    ]
}