{
    "last_update": "2026-06-11 11:29:10",
    "next_update": "2026-06-11 11:34:10",
    "domains": [
        {
            "domain": "miniyakin.com",
            "nawala": false,
            "network": false,
            "checked_at": "2026-06-11 11:28:59"
        },
        {
            "domain": "minitotobesar.site",
            "nawala": false,
            "network": false,
            "checked_at": "2026-06-11 11:29:00"
        },
        {
            "domain": "minipasticuan.com",
            "nawala": false,
            "network": false,
            "checked_at": "2026-06-11 11:29:01"
        },
        {
            "domain": "minimasihdisini.com",
            "nawala": false,
            "network": false,
            "checked_at": "2026-06-11 11:29:02"
        },
        {
            "domain": "minibisa.com",
            "nawala": false,
            "network": false,
            "checked_at": "2026-06-11 11:29:09"
        },
        {
            "domain": "minimantul.com",
            "nawala": false,
            "network": false,
            "checked_at": "2026-06-11 11:29:10"
        }
    ]
}